<?xml version="1.0"?>
<!DOCTYPE hibernate-mapping PUBLIC "-//Hibernate/Hibernate Mapping DTD 3.0//EN"
"http://hibernate.sourceforge.net/hibernate-mapping-3.0.dtd">
<!-- 
    Mapping file autogenerated by MyEclipse - Hibernate Tools
-->
<hibernate-mapping>
    <class name="et.po.SysStationInfo" table="sys_station_info">
        <id name="id" type="java.lang.String">
            <column name="id" length="50" />
            <generator class="assigned" />
        </id>
        <property name="departmentId" type="java.lang.String">
            <column name="department_id" length="50" />
        </property>
        <property name="depPersonName" type="java.lang.String">
            <column name="dep_person_name" length="50" />
        </property>
        <property name="depLevel" type="java.lang.String">
            <column name="dep_level" />
        </property>
        <property name="depDescribe" type="java.lang.String">
            <column name="dep_describe" />
        </property>
        <property name="remark" type="java.lang.String">
            <column name="remark" length="16277215" />
        </property>
    </class>
</hibernate-mapping>
